[
  {
    "adm2_name":"Tongariki",
    "adm2_code":"VUT0105083",
    "activity":"Aerial Assessment",
    "organisation":"SHEFA Provincial Council"
  },
  {
    "adm2_name":"Laika",
    "adm2_code":"VUT0105046",
    "activity":"Aerial Assessment",
    "organisation":"SHEFA Provincial Council"
  },
  {
    "adm2_name":"Tongoa",
    "adm2_code":"VUT0105026",
    "activity":"Aerial Assessment",
    "organisation":"SHEFA Provincial Council"
  },
  {
    "adm2_name":"Buninga",
    "adm2_code":"VUT0105037",
    "activity":"Aerial Assessment",
    "organisation":"SHEFA Provincial Council"
  },
  {
    "adm2_name":"Emae",
    "adm2_code":"VUT0105006",
    "activity":"Aerial Assessment",
    "organisation":"SHEFA Provincial Council"
  },
  {
    "adm2_name":"Makira",
    "adm2_code":"VUT0105015",
    "activity":"Aerial Assessment",
    "organisation":"SHEFA Provincial Council"
  },
  {
    "adm2_name":"Mataso - Matah Alam",
    "adm2_code":"VUT0105018",
    "activity":"Aerial Assessment",
    "organisation":"SHEFA Provincial Council"
  },
  {
    "adm2_name":"Etarik",
    "adm2_code":"VUT0105040",
    "activity":"Aerial Assessment",
    "organisation":"SHEFA Provincial Council"
  },
  {
    "adm2_name":"Pentecost",
    "adm2_code":"VUT0103022",
    "activity":"Aerial Assessment",
    "organisation":"Australian Defence Force"
  },
  {
    "adm2_name":"Ambae",
    "adm2_code":"VUT0103001",
    "activity":"Aerial Assessment",
    "organisation":"Australian Defence Force"
  },
  {
    "adm2_name":"0",
    "adm2_code":"#N/A",
    "activity":"Aerial Assessment",
    "organisation":"Unknown"
  },
  {
    "adm2_name":"0",
    "adm2_code":"#N/A",
    "activity":"Aerial Assessment",
    "organisation":"Unknown"
  },
  {
    "adm2_name":"0",
    "adm2_code":"#N/A",
    "activity":"Aerial Assessment",
    "organisation":"Unknown"
  },
  {
    "adm2_name":"0",
    "adm2_code":"#N/A",
    "activity":"Needs assessment mission",
    "organisation":"Joint National Disaster Management Office – Vanuatu Country Team"
  },
  {
    "adm2_name":"Tanna",
    "adm2_code":"VUT0106023",
    "activity":"Needs assessment mission",
    "organisation":"Joint National Disaster Management Office – Vanuatu Country Team"
  },
  {
    "adm2_name":"Aneityum",
    "adm2_code":"VUT0106003",
    "activity":"Needs assessment mission",
    "organisation":"Joint National Disaster Management Office – Vanuatu Country Team"
  },
  {
    "adm2_name":"Fortuna",
    "adm2_code":"VUT0106009",
    "activity":"Needs assessment mission",
    "organisation":"Joint National Disaster Management Office – Vanuatu Country Team"
  },
  {
    "adm2_name":"Erromango",
    "adm2_code":"VUT0106008",
    "activity":"Needs assessment mission",
    "organisation":"Joint National Disaster Management Office – Vanuatu Country Team"
  },
  {
    "adm2_name":"Pentecost",
    "adm2_code":"VUT0103022",
    "activity":"Needs assessment mission",
    "organisation":"Joint National Disaster Management Office – Vanuatu Country Team"
  },
  {
    "adm2_name":"Emae",
    "adm2_code":"VUT0105006",
    "activity":"Needs assessment mission",
    "organisation":"Joint National Disaster Management Office – Vanuatu Country Team"
  },
  {
    "adm2_name":"Ambrym",
    "adm2_code":"VUT0104002",
    "activity":"Needs assessment mission",
    "organisation":"National Disaster Management Office (NDMO)"
  },
  {
    "adm2_name":"Tongariki",
    "adm2_code":"VUT0105083",
    "activity":"Rapid Assessment",
    "organisation":"PCRAFI, Vanuatu Government, UNDAC"
  },
  {
    "adm2_name":"Laika",
    "adm2_code":"VUT0105046",
    "activity":"Rapid Assessment",
    "organisation":"PCRAFI, Vanuatu Government, UNDAC"
  },
  {
    "adm2_name":"Tongoa",
    "adm2_code":"VUT0105026",
    "activity":"Rapid Assessment",
    "organisation":"PCRAFI, Vanuatu Government, UNDAC"
  },
  {
    "adm2_name":"Buninga",
    "adm2_code":"VUT0105037",
    "activity":"Rapid Assessment",
    "organisation":"PCRAFI, Vanuatu Government, UNDAC"
  },
  {
    "adm2_name":"Emae",
    "adm2_code":"VUT0105006",
    "activity":"Rapid Assessment",
    "organisation":"PCRAFI, Vanuatu Government, UNDAC"
  },
  {
    "adm2_name":"Makira",
    "adm2_code":"VUT0105015",
    "activity":"Rapid Assessment",
    "organisation":"PCRAFI, Vanuatu Government, UNDAC"
  },
  {
    "adm2_name":"Mataso - Matah Alam",
    "adm2_code":"VUT0105018",
    "activity":"Rapid Assessment",
    "organisation":"PCRAFI, Vanuatu Government, UNDAC"
  },
  {
    "adm2_name":"Etarik",
    "adm2_code":"VUT0105040",
    "activity":"Rapid Assessment",
    "organisation":"PCRAFI, Vanuatu Government, UNDAC"
  },
  {
    "adm2_name":"Efate",
    "adm2_code":"VUT0105005",
    "activity":"Rapid Assessment",
    "organisation":"United Nations Disaster Assessment and Coordination"
  },
  {
    "adm2_name":"Efate",
    "adm2_code":"VUT0105005",
    "activity":"Rapid Assessment",
    "organisation":"United Nations Office for the Coordination of Humanitarian Affairs"
  },
  {
    "adm2_name":"Tanna",
    "adm2_code":"VUT0106023",
    "activity":"No Data",
    "organisation":"Telecoms Sans Frontieres"
  },
  {
    "adm2_name":"Ambrym",
    "adm2_code":"VUT0104002",
    "activity":"Needs assessment mission",
    "organisation":"Oxfam Australia"
  },
  {
    "adm2_name":"0",
    "adm2_code":"#N/A",
    "activity":"Needs assessment mission",
    "organisation":"Oxfam Australia"
  },
  {
    "adm2_name":"Epi",
    "adm2_code":"VUT0105007",
    "activity":"Needs assessment mission",
    "organisation":"Oxfam Australia"
  },
  {
    "adm2_name":"Pentecost",
    "adm2_code":"VUT0103022",
    "activity":"Needs assessment mission",
    "organisation":"Oxfam Australia"
  },
  {
    "adm2_name":"Efate",
    "adm2_code":"VUT0105005",
    "activity":"Needs assessment mission",
    "organisation":"Oxfam Australia"
  },
  {
    "adm2_name":"Efate",
    "adm2_code":"VUT0105005",
    "activity":"Needs assessment mission",
    "organisation":"Australian Military"
  },
  {
    "adm2_name":"Efate",
    "adm2_code":"VUT0105005",
    "activity":"Needs assessment mission",
    "organisation":"New Zealand Government"
  },
  {
    "adm2_name":"Santo",
    "adm2_code":"VUT0102029",
    "activity":"Needs assessment mission",
    "organisation":"World Vision"
  },
  {
    "adm2_name":"Tanna",
    "adm2_code":"VUT0106023",
    "activity":"Needs assessment mission",
    "organisation":"World Vision"
  },
  {
    "adm2_name":"Pentecost",
    "adm2_code":"VUT0103022",
    "activity":"Needs assessment mission",
    "organisation":"World Vision"
  },
  {
    "adm2_name":"Efate",
    "adm2_code":"VUT0105005",
    "activity":"Needs assessment mission",
    "organisation":"World Vision"
  },
  {
    "adm2_name":"Efate",
    "adm2_code":"VUT0105005",
    "activity":"No Data",
    "organisation":"Royal New Zealand Air Force"
  },
  {
    "adm2_name":"Efate",
    "adm2_code":"VUT0105005",
    "activity":"No Data",
    "organisation":"Royal Australian Air Force"
  },
  {
    "adm2_name":"Efate",
    "adm2_code":"VUT0105005",
    "activity":"No Data",
    "organisation":"Critical Care and Trauma Response Centre"
  },
  {
    "adm2_name":"Efate",
    "adm2_code":"VUT0105005",
    "activity":"Needs assessment mission",
    "organisation":"International Medical Corps"
  },
  {
    "adm2_name":"Efate",
    "adm2_code":"VUT0105005",
    "activity":"Rapid Assessment",
    "organisation":"The Pacific Humanitarian Team"
  },
  {
    "adm2_name":"Ambrym",
    "adm2_code":"VUT0104002",
    "activity":"Needs assessment mission",
    "organisation":"Solwata Club"
  },
  {
    "adm2_name":"Aniwa",
    "adm2_code":"VUT0106004",
    "activity":"No Data",
    "organisation":"Care International"
  },
  {
    "adm2_name":"Erromango",
    "adm2_code":"VUT0106008",
    "activity":"Needs assessment mission",
    "organisation":"Care International"
  },
  {
    "adm2_name":"Tanna",
    "adm2_code":"VUT0106023",
    "activity":"Needs assessment mission",
    "organisation":"TearFund New Zealand"
  },
  {
    "adm2_name":"Efate",
    "adm2_code":"VUT0105005",
    "activity":"Needs assessment mission",
    "organisation":"Volunteer Vanautu"
  },
  {
    "adm2_name":"Buninga",
    "adm2_code":"VUT0105037",
    "activity":"Needs assessment mission",
    "organisation":"Adventist Development and Relief Agency "
  },
  {
    "adm2_name":"Emae",
    "adm2_code":"VUT0105006",
    "activity":"Needs assessment mission",
    "organisation":"Adventist Development and Relief Agency "
  },
  {
    "adm2_name":"Laika",
    "adm2_code":"VUT0105046",
    "activity":"Needs assessment mission",
    "organisation":"Adventist Development and Relief Agency "
  },
  {
    "adm2_name":"Makira",
    "adm2_code":"VUT0105015",
    "activity":"Needs assessment mission",
    "organisation":"Adventist Development and Relief Agency "
  },
  {
    "adm2_name":"Mataso - Matah Alam",
    "adm2_code":"VUT0105018",
    "activity":"Needs assessment mission",
    "organisation":"Adventist Development and Relief Agency "
  },
  {
    "adm2_name":"Ewose",
    "adm2_code":"VUT0105102",
    "activity":"Needs assessment mission",
    "organisation":"Adventist Development and Relief Agency "
  },
  {
    "adm2_name":"Tongariki",
    "adm2_code":"VUT0105083",
    "activity":"Needs assessment mission",
    "organisation":"Adventist Development and Relief Agency "
  },
  {
    "adm2_name":"Tongoa",
    "adm2_code":"VUT0105026",
    "activity":"Needs assessment mission",
    "organisation":"Adventist Development and Relief Agency "
  },
  {
    "adm2_name":"0",
    "adm2_code":"#N/A",
    "activity":"Needs assessment mission",
    "organisation":"Adventist Development and Relief Agency "
  },
  {
    "adm2_name":"Pentecost",
    "adm2_code":"VUT0103022",
    "activity":"Needs assessment mission",
    "organisation":"Adventist Development and Relief Agency "
  },
  {
    "adm2_name":"Epi",
    "adm2_code":"VUT0105007",
    "activity":"Needs assessment mission",
    "organisation":"Adventist Development and Relief Agency "
  },
  {
    "adm2_name":"Tanna",
    "adm2_code":"VUT0106023",
    "activity":"Needs assessment mission",
    "organisation":"Adventist Development and Relief Agency "
  },
  {
    "adm2_name":"Efate",
    "adm2_code":"VUT0105005",
    "activity":"Needs assessment mission",
    "organisation":"Adventist Development and Relief Agency "
  },
  {
    "adm2_name":"Tanna",
    "adm2_code":"VUT0106023",
    "activity":"Needs assessment mission",
    "organisation":"Air Taxi Vanuatu"
  },
  {
    "adm2_name":"Efate",
    "adm2_code":"VUT0105005",
    "activity":"No Data",
    "organisation":"Red Cross Vanuatu"
  },
  {
    "adm2_name":"Efate",
    "adm2_code":"VUT0105005",
    "activity":"Needs assessment mission",
    "organisation":"Telecom Vanuatu Limited"
  },
  {
    "adm2_name":"Santo",
    "adm2_code":"VUT0102029",
    "activity":"Needs assessment mission",
    "organisation":"Telecom Vanuatu Limited"
  },
  {
    "adm2_name":"Tanna",
    "adm2_code":"VUT0106023",
    "activity":"Needs assessment mission",
    "organisation":"Telecom Vanuatu Limited"
  },
  {
    "adm2_name":"Efate",
    "adm2_code":"VUT0105005",
    "activity":"Rapid Assessment",
    "organisation":"Australian Urban Search and Rescue"
  },
  {
    "adm2_name":"Efate",
    "adm2_code":"VUT0105005",
    "activity":"Needs assessment mission",
    "organisation":"Australian Medical Assistance Team"
  },
  {
    "adm2_name":"Efate",
    "adm2_code":"VUT0105005",
    "activity":"Needs assessment mission",
    "organisation":"Kaleva Yachting Services Vanuatu"
  },
  {
    "adm2_name":"Mataso - Matah Alam",
    "adm2_code":"VUT0105018",
    "activity":"Rapid Assessment",
    "organisation":"International Organization for Migration"
  },
  {
    "adm2_name":"Efate",
    "adm2_code":"VUT0105005",
    "activity":"Rapid Assessment",
    "organisation":"International Organization for Migration"
  },
  {
    "adm2_name":"Efate",
    "adm2_code":"VUT0105005",
    "activity":"Needs assessment mission",
    "organisation":"ProMedical Vanuatu"
  },
  {
    "adm2_name":"Tanna",
    "adm2_code":"VUT0106023",
    "activity":"Needs assessment mission",
    "organisation":"TroppoDoc Charity"
  },
  {
    "adm2_name":"Efate",
    "adm2_code":"VUT0105005",
    "activity":"Needs assessment mission",
    "organisation":"World Animal Protection"
  },
  {
    "adm2_name":"Efate",
    "adm2_code":"VUT0105005",
    "activity":"Needs assessment mission",
    "organisation":"United Nations Children's Fund (UNICEF)"
  },
  {
    "adm2_name":"Santo",
    "adm2_code":"VUT0102029",
    "activity":"Needs assessment mission",
    "organisation":"United Nations Children's Fund (UNICEF)"
  },
  {
    "adm2_name":"Tanna",
    "adm2_code":"VUT0106023",
    "activity":"Needs assessment mission",
    "organisation":" les Forces armées de Nouvelle Calédonie "
  },
  {
    "adm2_name":"Efate",
    "adm2_code":"VUT0105005",
    "activity":"Needs assessment mission",
    "organisation":"Disaster Arborist Response Team"
  },
  {
    "adm2_name":"Efate",
    "adm2_code":"VUT0105005",
    "activity":"Needs assessment mission",
    "organisation":"Action Aid Australia"
  },
  {
    "adm2_name":"Tanna",
    "adm2_code":"VUT0106023",
    "activity":"Needs assessment mission",
    "organisation":"Digicel"
  },
  {
    "adm2_name":"Efate",
    "adm2_code":"VUT0105005",
    "activity":"No Data",
    "organisation":"P&O Cruises"
  },
  {
    "adm2_name":"Tanna",
    "adm2_code":"VUT0106023",
    "activity":"Needs assessment mission",
    "organisation":"RescueNet US"
  },
  {
    "adm2_name":"Efate",
    "adm2_code":"VUT0105005",
    "activity":"Needs assessment mission",
    "organisation":"Telsat Broadband Vanuatu"
  },
  {
    "adm2_name":"Efate",
    "adm2_code":"VUT0105005",
    "activity":"Needs assessment mission",
    "organisation":"United Nations Humanitarian Response Depot"
  },
  {
    "adm2_name":"Ambrym",
    "adm2_code":"VUT0104002",
    "activity":"Needs assessment mission",
    "organisation":"International medical Response UK"
  },
  {
    "adm2_name":"Efate",
    "adm2_code":"VUT0105005",
    "activity":"Needs assessment mission",
    "organisation":"International medical Response UK"
  },
  {
    "adm2_name":"Efate",
    "adm2_code":"VUT0105005",
    "activity":"Rapid Assessment",
    "organisation":"International Federation of Red Cross and Red Crescent Societies (IFRC)"
  },
  {
    "adm2_name":"Tanna",
    "adm2_code":"VUT0106023",
    "activity":"Rapid Assessment",
    "organisation":"International Federation of Red Cross and Red Crescent Societies (IFRC)"
  },
  {
    "adm2_name":"Moso",
    "adm2_code":"VUT0105065",
    "activity":"Rapid Assessment",
    "organisation":"International Federation of Red Cross and Red Crescent Societies (IFRC)"
  },
  {
    "adm2_name":"Lelepa",
    "adm2_code":"VUT0105051",
    "activity":"Rapid Assessment",
    "organisation":"International Federation of Red Cross and Red Crescent Societies (IFRC)"
  },
  {
    "adm2_name":"Emau",
    "adm2_code":"VUT0105039",
    "activity":"Rapid Assessment",
    "organisation":"International Federation of Red Cross and Red Crescent Societies (IFRC)"
  },
  {
    "adm2_name":"Nguna",
    "adm2_code":"VUT0105068",
    "activity":"Rapid Assessment",
    "organisation":"International Federation of Red Cross and Red Crescent Societies (IFRC)"
  },
  {
    "adm2_name":"Tongoa",
    "adm2_code":"VUT0105026",
    "activity":"Rapid Assessment",
    "organisation":"International Federation of Red Cross and Red Crescent Societies (IFRC)"
  },
  {
    "adm2_name":"Emae",
    "adm2_code":"VUT0105006",
    "activity":"Rapid Assessment",
    "organisation":"International Federation of Red Cross and Red Crescent Societies (IFRC)"
  },
  {
    "adm2_name":"Tongariki",
    "adm2_code":"VUT0105083",
    "activity":"Rapid Assessment",
    "organisation":"International Federation of Red Cross and Red Crescent Societies (IFRC)"
  },
  {
    "adm2_name":"Buninga",
    "adm2_code":"VUT0105037",
    "activity":"Rapid Assessment",
    "organisation":"International Federation of Red Cross and Red Crescent Societies (IFRC)"
  },
  {
    "adm2_name":"Makira",
    "adm2_code":"VUT0105015",
    "activity":"Rapid Assessment",
    "organisation":"International Federation of Red Cross and Red Crescent Societies (IFRC)"
  },
  {
    "adm2_name":"Mataso - Matah Alam",
    "adm2_code":"VUT0105018",
    "activity":"Rapid Assessment",
    "organisation":"International Federation of Red Cross and Red Crescent Societies (IFRC)"
  },
  {
    "adm2_name":"Malekula",
    "adm2_code":"VUT0104016",
    "activity":"Rapid Assessment",
    "organisation":"International Federation of Red Cross and Red Crescent Societies (IFRC)"
  },
  {
    "adm2_name":"Paama",
    "adm2_code":"VUT0104021",
    "activity":"Rapid Assessment",
    "organisation":"International Federation of Red Cross and Red Crescent Societies (IFRC)"
  },
  {
    "adm2_name":"Moso",
    "adm2_code":"VUT0105065",
    "activity":"Needs assessment mission",
    "organisation":"Save the Children"
  },
  {
    "adm2_name":"Lelepa",
    "adm2_code":"VUT0105051",
    "activity":"Needs assessment mission",
    "organisation":"Save the Children"
  },
  {
    "adm2_name":"Nguna",
    "adm2_code":"VUT0105068",
    "activity":"Needs assessment mission",
    "organisation":"Save the Children"
  },
  {
    "adm2_name":"Emau",
    "adm2_code":"VUT0105039",
    "activity":"Needs assessment mission",
    "organisation":"Save the Children"
  },
  {
    "adm2_name":"Efate",
    "adm2_code":"VUT0105005",
    "activity":"Needs assessment mission",
    "organisation":"Save the Children"
  },
  {
    "adm2_name":"Tongoa",
    "adm2_code":"VUT0105026",
    "activity":"Needs assessment mission",
    "organisation":"Save the Children"
  },
  {
    "adm2_name":"Epi",
    "adm2_code":"VUT0105007",
    "activity":"Needs assessment mission",
    "organisation":"Save the Children"
  },
  {
    "adm2_name":"Emae",
    "adm2_code":"VUT0105006",
    "activity":"Needs assessment mission",
    "organisation":"Save the Children"
  },
  {
    "adm2_name":"Tongariki",
    "adm2_code":"VUT0105083",
    "activity":"Needs assessment mission",
    "organisation":"Save the Children"
  },
  {
    "adm2_name":"Buninga",
    "adm2_code":"VUT0105037",
    "activity":"Needs assessment mission",
    "organisation":"Save the Children"
  },
  {
    "adm2_name":"Makira",
    "adm2_code":"VUT0105015",
    "activity":"Needs assessment mission",
    "organisation":"Save the Children"
  },
  {
    "adm2_name":"Mataso - Matah Alam",
    "adm2_code":"VUT0105018",
    "activity":"Needs assessment mission",
    "organisation":"Save the Children"
  },
  {
    "adm2_name":"Ambrym",
    "adm2_code":"VUT0104002",
    "activity":"Needs assessment mission",
    "organisation":"Save the Children"
  },
  {
    "adm2_name":"Malekula",
    "adm2_code":"VUT0104016",
    "activity":"Needs assessment mission",
    "organisation":"Save the Children"
  },
  {
    "adm2_name":"Paama",
    "adm2_code":"VUT0104021",
    "activity":"Needs assessment mission",
    "organisation":"Save the Children"
  },
  {
    "adm2_name":"Efate",
    "adm2_code":"VUT0105005",
    "activity":"Needs assessment mission",
    "organisation":"World Food Programme"
  },
  {
    "adm2_name":"Moso",
    "adm2_code":"VUT0105065",
    "activity":"Needs assessment mission",
    "organisation":"World Food Programme"
  },
  {
    "adm2_name":"Lelepa",
    "adm2_code":"VUT0105051",
    "activity":"Needs assessment mission",
    "organisation":"World Food Programme"
  },
  {
    "adm2_name":"Nguna",
    "adm2_code":"VUT0105068",
    "activity":"Needs assessment mission",
    "organisation":"World Food Programme"
  },
  {
    "adm2_name":"Emau",
    "adm2_code":"VUT0105039",
    "activity":"Needs assessment mission",
    "organisation":"World Food Programme"
  },
  {
    "adm2_name":"Tongoa",
    "adm2_code":"VUT0105026",
    "activity":"Needs assessment mission",
    "organisation":"World Food Programme"
  },
  {
    "adm2_name":"Epi",
    "adm2_code":"VUT0105007",
    "activity":"Needs assessment mission",
    "organisation":"World Food Programme"
  },
  {
    "adm2_name":"Emae",
    "adm2_code":"VUT0105006",
    "activity":"Needs assessment mission",
    "organisation":"World Food Programme"
  },
  {
    "adm2_name":"Tongariki",
    "adm2_code":"VUT0105083",
    "activity":"Needs assessment mission",
    "organisation":"World Food Programme"
  },
  {
    "adm2_name":"Buninga",
    "adm2_code":"VUT0105037",
    "activity":"Needs assessment mission",
    "organisation":"World Food Programme"
  },
  {
    "adm2_name":"Makira",
    "adm2_code":"VUT0105015",
    "activity":"Needs assessment mission",
    "organisation":"World Food Programme"
  },
  {
    "adm2_name":"Mataso - Matah Alam",
    "adm2_code":"VUT0105018",
    "activity":"Needs assessment mission",
    "organisation":"World Food Programme"
  },
  {
    "adm2_name":"Santo",
    "adm2_code":"VUT0102029",
    "activity":"Needs assessment mission",
    "organisation":"World Food Programme"
  },
  {
    "adm2_name":"Ambrym",
    "adm2_code":"VUT0104002",
    "activity":"Needs assessment mission",
    "organisation":"World Food Programme"
  },
  {
    "adm2_name":"Paama",
    "adm2_code":"VUT0104021",
    "activity":"Needs assessment mission",
    "organisation":"World Food Programme"
  },
  {
    "adm2_name":"Malekula",
    "adm2_code":"VUT0104016",
    "activity":"Needs assessment mission",
    "organisation":"World Food Programme"
  },
  {
    "adm2_name":"Ambae",
    "adm2_code":"VUT0103001",
    "activity":"Needs assessment mission",
    "organisation":"World Food Programme"
  },
  {
    "adm2_name":"Maewo",
    "adm2_code":"VUT0103014",
    "activity":"Needs assessment mission",
    "organisation":"World Food Programme"
  },
  {
    "adm2_name":"Pentecost",
    "adm2_code":"VUT0103022",
    "activity":"Needs assessment mission",
    "organisation":"World Food Programme"
  },
  {
    "adm2_name":"Aniwa",
    "adm2_code":"VUT0106004",
    "activity":"Needs assessment mission",
    "organisation":"World Food Programme"
  },
  {
    "adm2_name":"Fortuna",
    "adm2_code":"VUT0106009",
    "activity":"Needs assessment mission",
    "organisation":"World Food Programme"
  },
  {
    "adm2_name":"Erromango",
    "adm2_code":"VUT0106008",
    "activity":"Needs assessment mission",
    "organisation":"World Food Programme"
  },
  {
    "adm2_name":"Tanna",
    "adm2_code":"VUT0106023",
    "activity":"Needs assessment mission",
    "organisation":"World Food Programme"
  },
  {
    "adm2_name":"Tanna",
    "adm2_code":"VUT0106023",
    "activity":"Needs assessment mission",
    "organisation":"Vanuatu Red Cross Society"
  },
  {
    "adm2_name":"Aniwa",
    "adm2_code":"VUT0106004",
    "activity":"Needs assessment mission",
    "organisation":"Vanuatu Red Cross Society"
  },
  {
    "adm2_name":"Fortuna",
    "adm2_code":"VUT0106009",
    "activity":"Needs assessment mission",
    "organisation":"Vanuatu Red Cross Society"
  },
  {
    "adm2_name":"Erromango",
    "adm2_code":"VUT0106008",
    "activity":"Needs assessment mission",
    "organisation":"Vanuatu Red Cross Society"
  },
  {
    "adm2_name":"Aneityum",
    "adm2_code":"VUT0106003",
    "activity":"Needs assessment mission",
    "organisation":"Vanuatu Red Cross Society"
  },
  {
    "adm2_name":"Moso",
    "adm2_code":"VUT0105065",
    "activity":"Needs assessment mission",
    "organisation":"Vanuatu Red Cross Society"
  },
  {
    "adm2_name":"Lelepa",
    "adm2_code":"VUT0105051",
    "activity":"Needs assessment mission",
    "organisation":"Vanuatu Red Cross Society"
  },
  {
    "adm2_name":"Nguna",
    "adm2_code":"VUT0105068",
    "activity":"Needs assessment mission",
    "organisation":"Vanuatu Red Cross Society"
  },
  {
    "adm2_name":"Emau",
    "adm2_code":"VUT0105039",
    "activity":"Needs assessment mission",
    "organisation":"Vanuatu Red Cross Society"
  },
  {
    "adm2_name":"Efate",
    "adm2_code":"VUT0105005",
    "activity":"Needs assessment mission",
    "organisation":"Vanuatu Red Cross Society"
  },
  {
    "adm2_name":"Tongoa",
    "adm2_code":"VUT0105026",
    "activity":"Needs assessment mission",
    "organisation":"Vanuatu Red Cross Society"
  },
  {
    "adm2_name":"Epi",
    "adm2_code":"VUT0105007",
    "activity":"Needs assessment mission",
    "organisation":"Vanuatu Red Cross Society"
  },
  {
    "adm2_name":"Emae",
    "adm2_code":"VUT0105006",
    "activity":"Needs assessment mission",
    "organisation":"Vanuatu Red Cross Society"
  },
  {
    "adm2_name":"Tongariki",
    "adm2_code":"VUT0105083",
    "activity":"Needs assessment mission",
    "organisation":"Vanuatu Red Cross Society"
  },
  {
    "adm2_name":"Buninga",
    "adm2_code":"VUT0105037",
    "activity":"Needs assessment mission",
    "organisation":"Vanuatu Red Cross Society"
  },
  {
    "adm2_name":"Makira",
    "adm2_code":"VUT0105015",
    "activity":"Needs assessment mission",
    "organisation":"Vanuatu Red Cross Society"
  },
  {
    "adm2_name":"Mataso - Matah Alam",
    "adm2_code":"VUT0105018",
    "activity":"Needs assessment mission",
    "organisation":"Vanuatu Red Cross Society"
  },
  {
    "adm2_name":"Tongoa",
    "adm2_code":"VUT0105026",
    "activity":"Needs assessment mission",
    "organisation":"ACT for Peace / Vanuatu Council of Churches"
  },
  {
    "adm2_name":"Ambrym",
    "adm2_code":"VUT0104002",
    "activity":"Needs assessment mission",
    "organisation":"ACT for Peace / Vanuatu Council of Churches"
  },
  {
    "adm2_name":"Tanna",
    "adm2_code":"VUT0106023",
    "activity":"Needs assessment mission",
    "organisation":"ACT for Peace / Vanuatu Council of Churches"
  },
  {
    "adm2_name":"Moso",
    "adm2_code":"VUT0105065",
    "activity":"Needs assessment mission",
    "organisation":"World Health Organization (WHO)"
  },
  {
    "adm2_name":"Lelepa",
    "adm2_code":"VUT0105051",
    "activity":"Needs assessment mission",
    "organisation":"World Health Organization (WHO)"
  },
  {
    "adm2_name":"Nguna",
    "adm2_code":"VUT0105068",
    "activity":"Needs assessment mission",
    "organisation":"World Health Organization (WHO)"
  },
  {
    "adm2_name":"Emau",
    "adm2_code":"VUT0105039",
    "activity":"Needs assessment mission",
    "organisation":"World Health Organization (WHO)"
  },
  {
    "adm2_name":"Efate",
    "adm2_code":"VUT0105005",
    "activity":"Needs assessment mission",
    "organisation":"World Health Organization (WHO)"
  },
  {
    "adm2_name":"Tongoa",
    "adm2_code":"VUT0105026",
    "activity":"Needs assessment mission",
    "organisation":"World Health Organization (WHO)"
  },
  {
    "adm2_name":"Epi",
    "adm2_code":"VUT0105007",
    "activity":"Needs assessment mission",
    "organisation":"World Health Organization (WHO)"
  },
  {
    "adm2_name":"Emae",
    "adm2_code":"VUT0105006",
    "activity":"Needs assessment mission",
    "organisation":"World Health Organization (WHO)"
  },
  {
    "adm2_name":"Tongariki",
    "adm2_code":"VUT0105083",
    "activity":"Needs assessment mission",
    "organisation":"World Health Organization (WHO)"
  },
  {
    "adm2_name":"Buninga",
    "adm2_code":"VUT0105037",
    "activity":"Needs assessment mission",
    "organisation":"World Health Organization (WHO)"
  },
  {
    "adm2_name":"Makira",
    "adm2_code":"VUT0105015",
    "activity":"Needs assessment mission",
    "organisation":"World Health Organization (WHO)"
  },
  {
    "adm2_name":"Mataso - Matah Alam",
    "adm2_code":"VUT0105018",
    "activity":"Needs assessment mission",
    "organisation":"World Health Organization (WHO)"
  },
  {
    "adm2_name":"Erromango",
    "adm2_code":"VUT0106008",
    "activity":"Needs assessment mission",
    "organisation":"World Health Organization (WHO)"
  },
  {
    "adm2_name":"Aniwa",
    "adm2_code":"VUT0106004",
    "activity":"Needs assessment mission",
    "organisation":"World Health Organization (WHO)"
  },
  {
    "adm2_name":"Tanna",
    "adm2_code":"VUT0106023",
    "activity":"Needs assessment mission",
    "organisation":"World Health Organization (WHO)"
  },
  {
    "adm2_name":"Fortuna",
    "adm2_code":"VUT0106009",
    "activity":"Needs assessment mission",
    "organisation":"World Health Organization (WHO)"
  },
  {
    "adm2_name":"Ambrym",
    "adm2_code":"VUT0104002",
    "activity":"Needs assessment mission",
    "organisation":"World Health Organization (WHO)"
  },
  {
    "adm2_name":"Malekula",
    "adm2_code":"VUT0104016",
    "activity":"Needs assessment mission",
    "organisation":"World Health Organization (WHO)"
  },
  {
    "adm2_name":"Paama",
    "adm2_code":"VUT0104021",
    "activity":"Needs assessment mission",
    "organisation":"World Health Organization (WHO)"
  },
  {
    "adm2_name":"Ambae",
    "adm2_code":"VUT0103001",
    "activity":"Needs assessment mission",
    "organisation":"World Health Organization (WHO)"
  },
  {
    "adm2_name":"Maewo",
    "adm2_code":"VUT0103014",
    "activity":"Needs assessment mission",
    "organisation":"World Health Organization (WHO)"
  },
  {
    "adm2_name":"Pentecost",
    "adm2_code":"VUT0103022",
    "activity":"Needs assessment mission",
    "organisation":"World Health Organization (WHO)"
  },
  {
    "adm2_name":"Mere Lava",
    "adm2_code":"VUT0101019",
    "activity":"Needs assessment mission",
    "organisation":"World Health Organization (WHO)"
  },
  {
    "adm2_name":"Moso",
    "adm2_code":"VUT0105065",
    "activity":"Needs assessment mission",
    "organisation":"United Nations Population Fund (UNPF)"
  },
  {
    "adm2_name":"Lelepa",
    "adm2_code":"VUT0105051",
    "activity":"Needs assessment mission",
    "organisation":"United Nations Population Fund (UNPF)"
  },
  {
    "adm2_name":"Nguna",
    "adm2_code":"VUT0105068",
    "activity":"Needs assessment mission",
    "organisation":"United Nations Population Fund (UNPF)"
  },
  {
    "adm2_name":"Emau",
    "adm2_code":"VUT0105039",
    "activity":"Needs assessment mission",
    "organisation":"United Nations Population Fund (UNPF)"
  },
  {
    "adm2_name":"Efate",
    "adm2_code":"VUT0105005",
    "activity":"Needs assessment mission",
    "organisation":"United Nations Population Fund (UNPF)"
  },
  {
    "adm2_name":"Tongoa",
    "adm2_code":"VUT0105026",
    "activity":"Needs assessment mission",
    "organisation":"United Nations Population Fund (UNPF)"
  },
  {
    "adm2_name":"Epi",
    "adm2_code":"VUT0105007",
    "activity":"Needs assessment mission",
    "organisation":"United Nations Population Fund (UNPF)"
  },
  {
    "adm2_name":"Emae",
    "adm2_code":"VUT0105006",
    "activity":"Needs assessment mission",
    "organisation":"United Nations Population Fund (UNPF)"
  },
  {
    "adm2_name":"Tongariki",
    "adm2_code":"VUT0105083",
    "activity":"Needs assessment mission",
    "organisation":"United Nations Population Fund (UNPF)"
  },
  {
    "adm2_name":"Buninga",
    "adm2_code":"VUT0105037",
    "activity":"Needs assessment mission",
    "organisation":"United Nations Population Fund (UNPF)"
  },
  {
    "adm2_name":"Makira",
    "adm2_code":"VUT0105015",
    "activity":"Needs assessment mission",
    "organisation":"United Nations Population Fund (UNPF)"
  },
  {
    "adm2_name":"Mataso - Matah Alam",
    "adm2_code":"VUT0105018",
    "activity":"Needs assessment mission",
    "organisation":"United Nations Population Fund (UNPF)"
  },
  {
    "adm2_name":"Erromango",
    "adm2_code":"VUT0106008",
    "activity":"Needs assessment mission",
    "organisation":"United Nations Population Fund (UNPF)"
  },
  {
    "adm2_name":"Aniwa",
    "adm2_code":"VUT0106004",
    "activity":"Needs assessment mission",
    "organisation":"United Nations Population Fund (UNPF)"
  },
  {
    "adm2_name":"Tanna",
    "adm2_code":"VUT0106023",
    "activity":"Needs assessment mission",
    "organisation":"United Nations Population Fund (UNPF)"
  },
  {
    "adm2_name":"Fortuna",
    "adm2_code":"VUT0106009",
    "activity":"Needs assessment mission",
    "organisation":"United Nations Population Fund (UNPF)"
  },
  {
    "adm2_name":"Ambae",
    "adm2_code":"VUT0103001",
    "activity":"Needs assessment mission",
    "organisation":"United Nations Population Fund (UNPF)"
  },
  {
    "adm2_name":"Maewo",
    "adm2_code":"VUT0103014",
    "activity":"Needs assessment mission",
    "organisation":"United Nations Population Fund (UNPF)"
  },
  {
    "adm2_name":"Pentecost",
    "adm2_code":"VUT0103022",
    "activity":"Needs assessment mission",
    "organisation":"United Nations Population Fund (UNPF)"
  },
  {
    "adm2_name":"Santo",
    "adm2_code":"VUT0102029",
    "activity":"Needs assessment mission",
    "organisation":"United Nations Population Fund (UNPF)"
  },
  {
    "adm2_name":"Efate",
    "adm2_code":"VUT0105005",
    "activity":"Needs assessment mission",
    "organisation":"Unicef Supply Org"
  },
  {
    "adm2_name":"Epi",
    "adm2_code":"VUT0105007",
    "activity":"Needs assessment mission",
    "organisation":"UN Women"
  },
  {
    "adm2_name":"Tanna",
    "adm2_code":"VUT0106023",
    "activity":"Needs assessment mission",
    "organisation":"UN Women"
  },
  {
    "adm2_name":"Erromango",
    "adm2_code":"VUT0106008",
    "activity":"Needs assessment mission",
    "organisation":"UN Women"
  },
  {
    "adm2_name":"Erromango",
    "adm2_code":"VUT0106008",
    "activity":"Needs assessment mission",
    "organisation":"International Labour Organization"
  },
  {
    "adm2_name":"Tanna",
    "adm2_code":"VUT0106023",
    "activity":"Needs assessment mission",
    "organisation":"International Labour Organization"
  },
  {
    "adm2_name":"Efate",
    "adm2_code":"VUT0105005",
    "activity":"Needs assessment mission",
    "organisation":"International Labour Organization"
  },
  {
    "adm2_name":"Tongoa",
    "adm2_code":"VUT0105026",
    "activity":"Needs assessment mission",
    "organisation":"International Labour Organization"
  },
  {
    "adm2_name":"Epi",
    "adm2_code":"VUT0105007",
    "activity":"Needs assessment mission",
    "organisation":"International Labour Organization"
  },
  {
    "adm2_name":"Maewo",
    "adm2_code":"VUT0103014",
    "activity":"Needs assessment mission",
    "organisation":"UN High Commissioner for Human Rights (OHCHR)"
  },
  {
    "adm2_name":"Pentecost",
    "adm2_code":"VUT0103022",
    "activity":"Needs assessment mission",
    "organisation":"UN High Commissioner for Human Rights (OHCHR)"
  },
  {
    "adm2_name":"Ambrym",
    "adm2_code":"VUT0104002",
    "activity":"Needs assessment mission",
    "organisation":"UN High Commissioner for Human Rights (OHCHR)"
  },
  {
    "adm2_name":"Paama",
    "adm2_code":"VUT0104021",
    "activity":"Needs assessment mission",
    "organisation":"UN High Commissioner for Human Rights (OHCHR)"
  },
  {
    "adm2_name":"Moso",
    "adm2_code":"VUT0105065",
    "activity":"Needs assessment mission",
    "organisation":"UN High Commissioner for Human Rights (OHCHR)"
  },
  {
    "adm2_name":"Lelepa",
    "adm2_code":"VUT0105051",
    "activity":"Needs assessment mission",
    "organisation":"UN High Commissioner for Human Rights (OHCHR)"
  },
  {
    "adm2_name":"Nguna",
    "adm2_code":"VUT0105068",
    "activity":"Needs assessment mission",
    "organisation":"UN High Commissioner for Human Rights (OHCHR)"
  },
  {
    "adm2_name":"Emau",
    "adm2_code":"VUT0105039",
    "activity":"Needs assessment mission",
    "organisation":"UN High Commissioner for Human Rights (OHCHR)"
  },
  {
    "adm2_name":"Efate",
    "adm2_code":"VUT0105005",
    "activity":"Needs assessment mission",
    "organisation":"UN High Commissioner for Human Rights (OHCHR)"
  },
  {
    "adm2_name":"Tongoa",
    "adm2_code":"VUT0105026",
    "activity":"Needs assessment mission",
    "organisation":"UN High Commissioner for Human Rights (OHCHR)"
  },
  {
    "adm2_name":"Epi",
    "adm2_code":"VUT0105007",
    "activity":"Needs assessment mission",
    "organisation":"UN High Commissioner for Human Rights (OHCHR)"
  },
  {
    "adm2_name":"Emae",
    "adm2_code":"VUT0105006",
    "activity":"Needs assessment mission",
    "organisation":"UN High Commissioner for Human Rights (OHCHR)"
  },
  {
    "adm2_name":"Tongariki",
    "adm2_code":"VUT0105083",
    "activity":"Needs assessment mission",
    "organisation":"UN High Commissioner for Human Rights (OHCHR)"
  },
  {
    "adm2_name":"Buninga",
    "adm2_code":"VUT0105037",
    "activity":"Needs assessment mission",
    "organisation":"UN High Commissioner for Human Rights (OHCHR)"
  },
  {
    "adm2_name":"Makira",
    "adm2_code":"VUT0105015",
    "activity":"Needs assessment mission",
    "organisation":"UN High Commissioner for Human Rights (OHCHR)"
  },
  {
    "adm2_name":"Mataso - Matah Alam",
    "adm2_code":"VUT0105018",
    "activity":"Needs assessment mission",
    "organisation":"UN High Commissioner for Human Rights (OHCHR)"
  },
  {
    "adm2_name":"Erromango",
    "adm2_code":"VUT0106008",
    "activity":"Needs assessment mission",
    "organisation":"UN High Commissioner for Human Rights (OHCHR)"
  },
  {
    "adm2_name":"Aniwa",
    "adm2_code":"VUT0106004",
    "activity":"Needs assessment mission",
    "organisation":"UN High Commissioner for Human Rights (OHCHR)"
  },
  {
    "adm2_name":"Fortuna",
    "adm2_code":"VUT0106009",
    "activity":"Needs assessment mission",
    "organisation":"UN High Commissioner for Human Rights (OHCHR)"
  },
  {
    "adm2_name":"Tanna",
    "adm2_code":"VUT0106023",
    "activity":"Needs assessment mission",
    "organisation":"UN High Commissioner for Human Rights (OHCHR)"
  },
  {
    "adm2_name":"Efate",
    "adm2_code":"VUT0105005",
    "activity":"Needs assessment mission",
    "organisation":"United Nations Human Settlements Programme"
  },
  {
    "adm2_name":"Efate",
    "adm2_code":"VUT0105005",
    "activity":"Needs assessment mission",
    "organisation":"Secretariat of the Pacific Community (SPC)/GIZ climate change"
  },
  {
    "adm2_name":"Ambrym",
    "adm2_code":"VUT0104002",
    "activity":"Needs assessment mission",
    "organisation":"International Medical Corps"
  },
  {
    "adm2_name":"Moso",
    "adm2_code":"VUT0105065",
    "activity":"Needs assessment mission",
    "organisation":"United Nations Development Programme (UNDP) "
  },
  {
    "adm2_name":"Lelepa",
    "adm2_code":"VUT0105051",
    "activity":"Needs assessment mission",
    "organisation":"United Nations Development Programme (UNDP) "
  },
  {
    "adm2_name":"Nguna",
    "adm2_code":"VUT0105068",
    "activity":"Needs assessment mission",
    "organisation":"United Nations Development Programme (UNDP) "
  },
  {
    "adm2_name":"Emau",
    "adm2_code":"VUT0105039",
    "activity":"Needs assessment mission",
    "organisation":"United Nations Development Programme (UNDP) "
  },
  {
    "adm2_name":"Efate",
    "adm2_code":"VUT0105005",
    "activity":"Needs assessment mission",
    "organisation":"United Nations Development Programme (UNDP) "
  },
  {
    "adm2_name":"Tongoa",
    "adm2_code":"VUT0105026",
    "activity":"Needs assessment mission",
    "organisation":"United Nations Development Programme (UNDP) "
  },
  {
    "adm2_name":"Buninga",
    "adm2_code":"VUT0105037",
    "activity":"Needs assessment mission",
    "organisation":"United Nations Development Programme (UNDP) "
  },
  {
    "adm2_name":"Makira",
    "adm2_code":"VUT0105015",
    "activity":"Needs assessment mission",
    "organisation":"United Nations Development Programme (UNDP) "
  },
  {
    "adm2_name":"Mataso - Matah Alam",
    "adm2_code":"VUT0105018",
    "activity":"Needs assessment mission",
    "organisation":"United Nations Development Programme (UNDP) "
  },
  {
    "adm2_name":"Epi",
    "adm2_code":"VUT0105007",
    "activity":"Needs assessment mission",
    "organisation":"United Nations Development Programme (UNDP) "
  },
  {
    "adm2_name":"Emae",
    "adm2_code":"VUT0105006",
    "activity":"Needs assessment mission",
    "organisation":"United Nations Development Programme (UNDP) "
  },
  {
    "adm2_name":"Tongariki",
    "adm2_code":"VUT0105083",
    "activity":"Needs assessment mission",
    "organisation":"United Nations Development Programme (UNDP) "
  },
  {
    "adm2_name":"Aniwa",
    "adm2_code":"VUT0106004",
    "activity":"Needs assessment mission",
    "organisation":"United Nations Development Programme (UNDP) "
  },
  {
    "adm2_name":"Erromango",
    "adm2_code":"VUT0106008",
    "activity":"Needs assessment mission",
    "organisation":"United Nations Development Programme (UNDP) "
  },
  {
    "adm2_name":"Fortuna",
    "adm2_code":"VUT0106009",
    "activity":"Needs assessment mission",
    "organisation":"United Nations Development Programme (UNDP) "
  },
  {
    "adm2_name":"Tanna",
    "adm2_code":"VUT0106023",
    "activity":"Needs assessment mission",
    "organisation":"United Nations Development Programme (UNDP) "
  }
]